{
    "POST": {
        "/customers": "./json/customers/create.json",
        "/departments": "./json/departments/create.json",
        "/projects": "./json/projects/create.json",
        "/projectStatuses": "./json/projectStatuses/create.json",
        "/projectTypes": "./json/projectTypes/create.json",
        "/staffs": "./json/staffs/create.json",
        "/techStacks": "./json/techStacks/create.json",
        "/users": "./json/users/create.json",
        "/auth/login": "./json/auth/login.json"
    }, 
    "PUT": {
        "/api/customers/:id": "./json/customers/update.json",
        "/api/departments/:id": "./json/departments/update.json",
        "/api/projects/:id": "./json/projects/update.json",
        "/api/projectStatuses/:id": "./json/projectStatuses/update.json",
        "/api/projectTypes/:id": "./json/projectTypes/update.json",
        "/api/staffs/:id": "./json/staffs/update.json",
        "/api/techStacks/:id": "./json/techStacks/update.json"
    }
}